{
  "date": "2026-07-14",
  "irrigation": {
    "logs": [
      [
        2,
        2,
        1800,
        1784014201
      ],
      [
        2,
        3,
        1800,
        1784016001
      ],
      [
        3,
        2,
        600,
        1784049001
      ],
      [
        3,
        3,
        600,
        1784049601
      ]
    ]
  },
  "weather": {
    "precip_total_in": 0.14,
    "temp_high_f": 85.8,
    "temp_low_f": 56.2,
    "temp_avg_f": 71.7,
    "humidity_avg_pct": 51.9
  }
}